pytofi-0.0.1.dist-info/licenses/LICENSE
tofi/__init__.py
tofi/crosser.py
tofi/inferer.py
tofi/utils.py
pytofi-0.0.1.dist-info/METADATA
pytofi-0.0.1.dist-info/WHEEL
pytofi-0.0.1.dist-info/top_level.txt
pytofi-0.0.1.dist-info/RECORD
